smush/__init__.py
smush/app.py
smush/git_log_style_checker.py
smush/topicmerge.py
smush-0.0.7.data/scripts/smush
smush-0.0.7.dist-info/LICENSE
smush-0.0.7.dist-info/METADATA
smush-0.0.7.dist-info/WHEEL
smush-0.0.7.dist-info/top_level.txt
smush-0.0.7.dist-info/RECORD
