Metadata-Version: 2.1
Name: smush
Version: 0.0.7
Summary: Tool to automate merging of topic branches
Home-page: https://github.com/artefactual-labs/smush
Author: Mike Cantelon
Author-email: mcantelon@gmail.com
License: MIT
Keywords: git
Platform: UNKNOWN
